pyreckless/__init__.py
pyreckless-0.1.0.dist-info/METADATA
pyreckless-0.1.0.dist-info/WHEEL
pyreckless-0.1.0.dist-info/top_level.txt
pyreckless-0.1.0.dist-info/RECORD
